odoo/addons/sale_stock_info_popup/README.rst
odoo/addons/sale_stock_info_popup/__init__.py
odoo/addons/sale_stock_info_popup/__manifest__.py
odoo/addons/sale_stock_info_popup/i18n/es.po
odoo/addons/sale_stock_info_popup/i18n/sale_stock_info_popup.pot
odoo/addons/sale_stock_info_popup/models/__init__.py
odoo/addons/sale_stock_info_popup/models/product.py
odoo/addons/sale_stock_info_popup/models/sale_order.py
odoo/addons/sale_stock_info_popup/readme/CONTRIBUTORS.rst
odoo/addons/sale_stock_info_popup/readme/DESCRIPTION.rst
odoo/addons/sale_stock_info_popup/readme/USAGE.rst
odoo/addons/sale_stock_info_popup/static/description/icon.png
odoo/addons/sale_stock_info_popup/static/description/index.html
odoo/addons/sale_stock_info_popup/static/src/img/info-circle-solid.png
odoo/addons/sale_stock_info_popup/static/src/js/qty_at_date_widget.js
odoo/addons/sale_stock_info_popup/static/src/xml/qty_at_date.xml
odoo/addons/sale_stock_info_popup/tests/__init__.py
odoo/addons/sale_stock_info_popup/tests/test_sale_stock_info_popup.py
odoo/addons/sale_stock_info_popup/views/assets.xml
odoo/addons/sale_stock_info_popup/views/sale_order_views.xml
odoo12_addon_sale_stock_info_popup-12.0.1.0.2.dist-info/METADATA
odoo12_addon_sale_stock_info_popup-12.0.1.0.2.dist-info/WHEEL
odoo12_addon_sale_stock_info_popup-12.0.1.0.2.dist-info/top_level.txt
odoo12_addon_sale_stock_info_popup-12.0.1.0.2.dist-info/RECORD
