Metadata-Version: 2.1
Name: odoo12-addon-sale-stock-info-popup
Version: 12.0.1.0.2
Summary: Adds a popover in sale order line to display stock info of the product
Home-page: https://github.com/OCA/stock-logistics-warehouse
Author: Odoo S.A., Tecnativa, Odoo Community Association (OCA)
Author-email: support@odoo-community.org
License: AGPL-3
Platform: UNKNOWN
Classifier: Programming Language :: Python
Classifier: Framework :: Odoo
Classifier: License :: OSI Approved :: GNU Affero General Public License v3
Requires-Python: >=3.5
Requires-Dist: odoo (<12.1dev,>=12.0a)
